Inspyctor/__init__.py
Inspyctor/analyzers.py
Inspyctor/cli.py
Inspyctor/review.py
inspyctor-0.2.0.dist-info/METADATA
inspyctor-0.2.0.dist-info/WHEEL
inspyctor-0.2.0.dist-info/entry_points.txt
inspyctor-0.2.0.dist-info/top_level.txt
inspyctor-0.2.0.dist-info/RECORD
