Metadata-Version: 2.1
Name: inspyctor
Version: 0.2.0
Summary: Command-line tool to review Python code for style and security.
Home-page: https://github.com/abhishekchaudharygh/inspyctor
Author: Abhishek Chaudhary
Author-email: abhishekchaudhary1403@gmail.com
Classifier: Programming Language :: Python :: 3
Classifier: License :: OSI Approved :: MIT License
Classifier: Programming Language :: Python :: 3.8
Requires-Python: >=3.6
Requires-Dist: flake8
Requires-Dist: bandit
